qtpy_led/__init__.py
qtpy_led/qtpy_led.py
qtpy_led/test.py
qtpy_led-0.1.2.dist-info/LICENSE
qtpy_led-0.1.2.dist-info/WHEEL
qtpy_led-0.1.2.dist-info/METADATA
qtpy_led-0.1.2.dist-info/RECORD
