Metadata-Version: 2.1
Name: qtpy-led
Version: 0.1.2
Summary: Simple LED widget for QyPt
Home-page: https://github.com/crash8229/qtpy_led
License: MIT
Author: crash8229
Author-email: mu304007@gmail.com
Requires-Python: >=3.8,<4.0
Classifier: License :: OSI Approved :: MIT License
Classifier: Programming Language :: Python :: 3
Classifier: Programming Language :: Python :: 3.8
Classifier: Programming Language :: Python :: 3.9
Classifier: Programming Language :: Python :: 3.10
Requires-Dist: PyAutoGUI (>=0.9.53,<0.10.0)
Requires-Dist: QtPy (>=2.3.0,<3.0.0)
Requires-Dist: numpy (>=1.24.2,<2.0.0)
Project-URL: Repository, https://github.com/crash8229/qtpy_led
